riskx/__init__.py
riskx/cli/__init__.py
riskx/cli/main.py
riskx/core/data_cleaner.py
riskx/core/data_connector.py
riskx/core/explainability.py
riskx/core/feature_engineering.py
riskx/core/model_auto.py
riskx/core/monitoring.py
riskx/core/scoring_engine.py
riskx/deployment/__init__.py
riskx/deployment/cloud_deploy.py
riskx/metrics/__init__.py
riskx/metrics/evaluation.py
riskx/pipelines/__init__.py
riskx/pipelines/risk_pipeline.py
riskx-0.1.1.dist-info/licenses/LICENSE
riskx-0.1.1.dist-info/METADATA
riskx-0.1.1.dist-info/WHEEL
riskx-0.1.1.dist-info/entry_points.txt
riskx-0.1.1.dist-info/top_level.txt
riskx-0.1.1.dist-info/RECORD
