Metadata-Version: 2.4
Name: riskx
Version: 0.1.1
Summary: End-to-End Automated Risk Scoring Platform for Credit, Fraud, and Churn Prediction
Home-page: https://github.com/idrissbado/RiskX
Author: Idriss Bado
Author-email: Idriss Bado <idrissbadoolivier@gmail.com>
License: MIT
Project-URL: Homepage, https://github.com/idrissbado/RiskX
Project-URL: Documentation, https://github.com/idrissbado/RiskX/blob/main/README.md
Project-URL: Repository, https://github.com/idrissbado/RiskX
Project-URL: Issues, https://github.com/idrissbado/RiskX/issues
Keywords: risk-scoring,credit-scoring,fraud-detection,ml,automl,risk-management,financial-risk
Classifier: Development Status :: 4 - Beta
Classifier: Intended Audience :: Developers
Classifier: Intended Audience :: Financial and Insurance Industry
Classifier: Intended Audience :: Science/Research
Classifier: Topic :: Scientific/Engineering :: Artificial Intelligence
Classifier: Topic :: Office/Business :: Financial
Classifier: License :: OSI Approved :: MIT License
Classifier: Programming Language :: Python :: 3
Classifier: Programming Language :: Python :: 3.8
Classifier: Programming Language :: Python :: 3.9
Classifier: Programming Language :: Python :: 3.10
Classifier: Programming Language :: Python :: 3.11
Classifier: Operating System :: OS Independent
Requires-Python: >=3.8
License-File: LICENSE
Requires-Dist: pandas>=1.3.0
Requires-Dist: numpy>=1.21.0
Requires-Dist: scikit-learn>=1.0.0
Provides-Extra: full
Requires-Dist: xgboost>=1.5.0; extra == "full"
Requires-Dist: lightgbm>=3.3.0; extra == "full"
Requires-Dist: optuna>=2.10.0; extra == "full"
Requires-Dist: shap>=0.40.0; extra == "full"
Requires-Dist: sqlalchemy>=1.4.0; extra == "full"
Requires-Dist: requests>=2.26.0; extra == "full"
Requires-Dist: pyarrow>=6.0.0; extra == "full"
Provides-Extra: ml
Requires-Dist: xgboost>=1.5.0; extra == "ml"
Requires-Dist: lightgbm>=3.3.0; extra == "ml"
Requires-Dist: optuna>=2.10.0; extra == "ml"
Provides-Extra: data
Requires-Dist: sqlalchemy>=1.4.0; extra == "data"
Requires-Dist: requests>=2.26.0; extra == "data"
Requires-Dist: pyarrow>=6.0.0; extra == "data"
Requires-Dist: openpyxl>=3.0.0; extra == "data"
Provides-Extra: explain
Requires-Dist: shap>=0.40.0; extra == "explain"
Provides-Extra: azure
Requires-Dist: azure-ai-ml>=1.0.0; extra == "azure"
Requires-Dist: azure-identity>=1.10.0; extra == "azure"
Provides-Extra: aws
Requires-Dist: boto3>=1.20.0; extra == "aws"
Provides-Extra: gcp
Requires-Dist: google-cloud-run>=0.5.0; extra == "gcp"
Provides-Extra: dev
Requires-Dist: pytest>=7.0.0; extra == "dev"
Requires-Dist: pytest-cov>=3.0.0; extra == "dev"
Requires-Dist: black>=22.0.0; extra == "dev"
Requires-Dist: flake8>=4.0.0; extra == "dev"
Requires-Dist: mypy>=0.950; extra == "dev"
Dynamic: author
Dynamic: home-page
Dynamic: license-file
Dynamic: requires-python
